[
    {
        "name": "하랑짱",
        "pos": "휴직",
        "profile_image": "https://storage2.ygosu.com/?code=S696b61f365c0e3.11842146",
        "title": "[YB]  낮빵♥",
        "viewers": 129,
        "start_time": "2026-07-23T05:27:28.000Z",
        "thumbnail": "https://liveimg.sooplive.com/h/295789327.webp",
        "live_link": "https://play.sooplive.com/asy1218/295789327"
    },
    {
        "name": "아름",
        "pos": "선임사원",
        "profile_image": "https://storage2.ygosu.com/?code=S69f0a918af6ab2.84500064",
        "title": "[YB]나오늘 렌즈안꼇는데.. 어떄? 슬립방셀2892♥",
        "viewers": 97,
        "start_time": "2026-07-23T04:22:45.000Z",
        "thumbnail": "https://liveimg.sooplive.com/h/295788119.webp",
        "live_link": "https://play.sooplive.com/ahrum0912/295788119"
    },
    {
        "name": "꺼니",
        "pos": "웨이터",
        "profile_image": "https://storage2.ygosu.com/?code=S69f0a951064842.70871652",
        "title": "[YB] 벤티타고 해남가서 술먹방 2일차 오는 사람 선착순 1명 3만개+@ 해남살이 육하원칙중!",
        "viewers": 64,
        "start_time": "2026-07-23T03:45:26.000Z",
        "thumbnail": "https://liveimg.sooplive.com/h/295787509.webp",
        "live_link": "https://play.sooplive.com/callgg/295787509"
    }
]