[
    {
        "name": "염보성",
        "pos": "대표",
        "profile_image": "https://storage2.ygosu.com/?code=S68dbfbfc3f44e8.21921692",
        "title": "염보성엑셀출근방송(YXL)",
        "viewers": 2292,
        "start_time": "2026-06-16T03:03:21.000Z",
        "thumbnail": "https://liveimg.sooplive.com/h/294854219.webp",
        "live_link": "https://play.sooplive.com/yuambo/294854219"
    },
    {
        "name": "서니",
        "pos": "시급이",
        "profile_image": "https://storage2.ygosu.com/?code=S69f0a954b0c8f6.90064035",
        "title": "[YXL 시급] 오늘 직프다 .. 시급탈출 제발 ㅠ.ㅠ",
        "viewers": 104,
        "start_time": "2026-06-18T06:26:49.000Z",
        "thumbnail": "https://liveimg.sooplive.com/h/294909939.webp",
        "live_link": "https://play.sooplive.com/iluvpp/294909939"
    },
    {
        "name": "너의멜로디",
        "pos": "비서실장",
        "profile_image": "https://storage2.ygosu.com/?code=S69cb6c7203b578.77318633",
        "title": "[YXL:비실] 직프 잿팟데이 출근방송 on",
        "viewers": 130,
        "start_time": "2026-06-18T04:47:24.000Z",
        "thumbnail": "https://liveimg.sooplive.com/h/294907989.webp",
        "live_link": "https://play.sooplive.com/meldoy777/294907989"
    }
]