[
    {
        "user_nick": "꺼니",
        "title": "오방공",
        "date": "2026-06-02 23:30:53",
        "read_cnt": 131,
        "like_cnt": 11,
        "comment_cnt": 5,
        "profile_image": "https://profile.img.sooplive.com/LOGO/ca/callgg/callgg.jpg",
        "link": "https://www.sooplive.com/station/callgg/post/197541495"
    },
    {
        "user_nick": "첨지쿤",
        "title": "제드입니다",
        "date": "2026-06-02 22:29:45",
        "read_cnt": 25,
        "like_cnt": 3,
        "comment_cnt": 0,
        "profile_image": "https://profile.img.sooplive.com/LOGO/rl/rlarkdgus231/rlarkdgus231.jpg",
        "link": "https://www.sooplive.com/station/yuambo/post/197533867"
    },
    {
        "user_nick": "류서하♥",
        "title": "오밤공",
        "date": "2026-06-02 22:03:21",
        "read_cnt": 74,
        "like_cnt": 8,
        "comment_cnt": 3,
        "profile_image": "https://profile.img.sooplive.com/LOGO/sm/smkim82372/smkim82372.jpg",
        "link": "https://www.sooplive.com/station/smkim82372/post/197530595"
    },
    {
        "user_nick": "미로。",
        "title": "2부 생일",
        "date": "2026-06-02 20:00:27",
        "read_cnt": 55,
        "like_cnt": 9,
        "comment_cnt": 1,
        "profile_image": "https://profile.img.sooplive.com/LOGO/fh/fhwm0602/fhwm0602.jpg",
        "link": "https://www.sooplive.com/station/fhwm0602/post/197515929"
    },
    {
        "user_nick": "아름[♥]",
        "title": "오방공",
        "date": "2026-06-02 19:21:25",
        "read_cnt": 59,
        "like_cnt": 13,
        "comment_cnt": 0,
        "profile_image": "https://profile.img.sooplive.com/LOGO/ah/ahrum0912/ahrum0912.jpg",
        "link": "https://www.sooplive.com/station/ahrum0912/post/197511845"
    },
    {
        "user_nick": "후잉♥",
        "title": "하요",
        "date": "2026-06-02 17:18:22",
        "read_cnt": 264,
        "like_cnt": 26,
        "comment_cnt": 15,
        "profile_image": "https://profile.img.sooplive.com/LOGO/ja/jaeha010/jaeha010.jpg",
        "link": "https://www.sooplive.com/station/jaeha010/post/197500621"
    },
    {
        "user_nick": "망㉦령",
        "title": "김유정 갠방시그검색 사이트",
        "date": "2026-06-02 17:12:07",
        "read_cnt": 5,
        "like_cnt": 1,
        "comment_cnt": 0,
        "profile_image": "https://profile.img.sooplive.com/LOGO/bl/blackpig123/blackpig123.jpg",
        "link": "https://www.sooplive.com/station/tkek55/post/197500063"
    },
    {
        "user_nick": "냥냥수주",
        "title": "얘두라!",
        "date": "2026-06-02 14:07:38",
        "read_cnt": 452,
        "like_cnt": 59,
        "comment_cnt": 25,
        "profile_image": "https://profile.img.sooplive.com/LOGO/st/star49/star49.jpg",
        "link": "https://www.sooplive.com/station/star49/post/197488509"
    },
    {
        "user_nick": "서니_♥",
        "title": "오늘",
        "date": "2026-06-02 10:13:12",
        "read_cnt": 145,
        "like_cnt": 15,
        "comment_cnt": 1,
        "profile_image": "https://profile.img.sooplive.com/LOGO/il/iluvpp/iluvpp.jpg",
        "link": "https://www.sooplive.com/station/iluvpp/post/197479203"
    },
    {
        "user_nick": "너의˚멜로디",
        "title": "이번주 휴방공디 :)",
        "date": "2026-06-01 17:32:32",
        "read_cnt": 409,
        "like_cnt": 43,
        "comment_cnt": 10,
        "profile_image": "https://profile.img.sooplive.com/LOGO/me/meldoy777/meldoy777.jpg",
        "link": "https://www.sooplive.com/station/meldoy777/post/197407141"
    },
    {
        "user_nick": "[H]치즈",
        "title": "🚬",
        "date": "2026-05-30 17:14:44",
        "read_cnt": 64,
        "like_cnt": 3,
        "comment_cnt": 0,
        "profile_image": "https://profile.img.sooplive.com/LOGO/im/imimim555/imimim555.jpg",
        "link": "https://www.sooplive.com/station/wk3220/post/197201895"
    },
    {
        "user_nick": "김푸:)",
        "title": "오방공!",
        "date": "2026-05-27 21:58:37",
        "read_cnt": 54,
        "like_cnt": 13,
        "comment_cnt": 0,
        "profile_image": "https://profile.img.sooplive.com/LOGO/ki/kimpooh0707/kimpooh0707.jpg",
        "link": "https://www.sooplive.com/station/kimpooh0707/post/196941929"
    },
    {
        "user_nick": "소다♥",
        "title": "소데기 방송 O N",
        "date": "2026-05-22 21:36:47",
        "read_cnt": 51,
        "like_cnt": 12,
        "comment_cnt": 0,
        "profile_image": "https://profile.img.sooplive.com/LOGO/zb/zbxlzzz/zbxlzzz.jpg",
        "link": "https://www.sooplive.com/station/zbxlzzz/post/196461849"
    },
    {
        "user_nick": "하랑짱♥",
        "title": "오방공 수정",
        "date": "2026-05-17 14:07:50",
        "read_cnt": 184,
        "like_cnt": 27,
        "comment_cnt": 4,
        "profile_image": "https://profile.img.sooplive.com/LOGO/as/asy1218/asy1218.jpg",
        "link": "https://www.sooplive.com/station/asy1218/post/195954619"
    }
]